passphera_shell/__init__.py
passphera_shell/entities.py
passphera_shell/exceptions.py
passphera_shell/interfaces.py
passphera_shell/application/__init__.py
passphera_shell/application/generator.py
passphera_shell/application/vault.py
passphera_shell-0.5.0.dist-info/licenses/LICENSE
passphera_shell-0.5.0.dist-info/METADATA
passphera_shell-0.5.0.dist-info/WHEEL
passphera_shell-0.5.0.dist-info/top_level.txt
passphera_shell-0.5.0.dist-info/RECORD
