Metadata-Version: 2.4
Name: passphera-shell
Version: 0.5.0
Summary: The shell contain the use cases and interfaces of passphera project
Home-page: https://github.com/passphera/shell
Author: Fathi Abdelmalek
Author-email: passphera@imfathi.com
Classifier: Development Status :: 3 - Alpha
Classifier: License :: OSI Approved :: Apache Software License
Classifier: Operating System :: OS Independent
Classifier: Programming Language :: Python
Classifier: Programming Language :: Python :: 3
Classifier: Topic :: Security
Classifier: Topic :: Security :: Cryptography
Requires-Python: >=3
License-File: LICENSE
Requires-Dist: passphera-core
Requires-Dist: cryptography
Dynamic: author
Dynamic: author-email
Dynamic: classifier
Dynamic: description-content-type
Dynamic: home-page
Dynamic: license-file
Dynamic: requires-dist
Dynamic: requires-python
Dynamic: summary
